qualiti/ai.py
qualiti/async_typer.py
qualiti/attributer.py
qualiti/cli.py
qualiti/config.py
qualiti/display.py
qualiti/huggingface.py
qualiti/qualiti.conf.json
qualiti/utils.py
qualiti-0.1.0.dist-info/LICENSE
qualiti-0.1.0.dist-info/METADATA
qualiti-0.1.0.dist-info/WHEEL
qualiti-0.1.0.dist-info/entry_points.txt
qualiti-0.1.0.dist-info/RECORD
