Metadata-Version: 2.1
Name: qualiti
Version: 0.1.0
Summary: Qualiti.ai Python Tools
Author: Carlos Kidman
Author-email: ckidman@qualiti.ai
Requires-Python: >=3.8.12,<4.0
Classifier: Programming Language :: Python :: 3
Classifier: Programming Language :: Python :: 3.9
Classifier: Programming Language :: Python :: 3.10
Classifier: Programming Language :: Python :: 3.11
Requires-Dist: asyncio (>=3.4.3,<4.0.0)
Requires-Dist: datasets (>=2.12.0,<3.0.0)
Requires-Dist: openai (>=0.27.5,<0.28.0)
Requires-Dist: python-dotenv (>=1.0.0,<2.0.0)
Requires-Dist: sentence-transformers (>=2.2.2,<3.0.0)
Requires-Dist: transformers[agents] (>=4.29.2,<5.0.0)
Requires-Dist: typer[all] (>=0.8.0,<0.9.0)
